indicpy/__init__.py
indicpy/__main__.py
indicpy/exceptions.py
indicpy/indicpy.py
indicpy/language.py
indicpy/main.py
indicpy/test.py
indicpy/examples/english.py
indicpy/examples/hindi.pyhi
indicpy/examples/hindi_english.epyhi
indicpy/examples/kannada.pykn
indicpy/examples/kannada_english.epykn
indicpy/keywords/hindi.yml
indicpy/keywords/hindi_english.yml
indicpy/keywords/kannada.yml
indicpy/keywords/kannada_english.yml
indicpy-1.0.0.dist-info/LICENSE
indicpy-1.0.0.dist-info/METADATA
indicpy-1.0.0.dist-info/WHEEL
indicpy-1.0.0.dist-info/top_level.txt
indicpy-1.0.0.dist-info/RECORD
