Metadata-Version: 2.1
Name: indicpy
Version: 1.0.0
Summary: A Python library for running Indic Python Scripts
Home-page: UNKNOWN
Author: Suprad S Parashar
Author-email: suprad.s.parashar@gmail.com
License: UNKNOWN
Keywords: python,indian,local,indic,dravidian,devanagari,scripts
Platform: UNKNOWN
Classifier: Development Status :: 1 - Planning
Classifier: Intended Audience :: Developers
Classifier: Programming Language :: Python :: 3
Classifier: Operating System :: Unix
Classifier: Operating System :: MacOS :: MacOS X
Classifier: Operating System :: Microsoft :: Windows
License-File: LICENSE
Requires-Dist: argparse
